sudoku/__init__.py
sudoku/base_sudoku.py
sudoku/exceptions.py
sudoku/variations/__init__.py
sudoku/variations/classic_sudoku.py
sudoku/variations/diagonal_sudoku.py
sudoku_engine-2.0.0.dist-info/licenses/LICENSE
sudoku_engine-2.0.0.dist-info/METADATA
sudoku_engine-2.0.0.dist-info/WHEEL
sudoku_engine-2.0.0.dist-info/top_level.txt
sudoku_engine-2.0.0.dist-info/RECORD
