Metadata-Version: 2.4
Name: sudoku-engine
Version: 2.0.0
Summary: A simple Python package that generates and solves m x n Sudoku puzzles.
Author-email: Sepehr Rasouli <sepehrrasouli06@gmail.com>
License: MIT License
Project-URL: Homepage, https://github.com/sepehr-rs/sudoku-engine
Project-URL: Issues, https://github.com/sepehr-rs/sudoku-engine/issues
Project-URL: GitHub, https://github.com/sepehr-rs/sudoku-engine/py-sudoku
Keywords: SUDOKU
Classifier: Programming Language :: Python :: 3
Classifier: License :: OSI Approved :: MIT License
Classifier: Operating System :: OS Independent
Requires-Python: >=3.8
License-File: LICENSE
Dynamic: license-file
